Showcase-0.3.4.dist-info/DESCRIPTION.rst
Showcase-0.3.4.dist-info/METADATA
Showcase-0.3.4.dist-info/RECORD
Showcase-0.3.4.dist-info/WHEEL
Showcase-0.3.4.dist-info/metadata.json
Showcase-0.3.4.dist-info/top_level.txt
showcase/__init__.py
showcase/app.py
showcase/utils.py
showcase/static/css/normalize.css
showcase/static/css/skeleton.css
showcase/templates/base.html
showcase/templates/dir.html
showcase/templates/file.html
