Metadata-Version: 2.0
Name: Showcase
Version: 0.3.4
Summary: Like SimpleHTTPServer, only worse
Home-page: UNKNOWN
Author: James Rutherford
Author-email: jim@jimr.org
License: UNKNOWN
Platform: UNKNOWN
Classifier: Development Status :: 3 - Alpha
Classifier: Intended Audience :: Developers
Classifier: Topic :: Utilities
Classifier: License :: OSI Approved :: MIT License
Classifier: Programming Language :: Python :: 2
Classifier: Programming Language :: Python :: 3
Requires-Dist: Flask (==0.12)
Requires-Dist: chardet (==2.3.0)
Requires-Dist: gunicorn (==19.7.0)
Requires-Dist: humanize (==0.5.1)
